[
  {
    "type": "branding",
    "title": "AI時代のマネジャーの役割変革：若手がAIを信頼する時代にマネジャーが持つべき「人間的価値」とは",
    "target_reader": "マネジャー・管理職、経営層、人事担当者",
    "angle": "若手社員が上司よりもAIに相談することを信頼する傾向や、課長のAI活用実態から、AIと共存するマネジャーが自身の人間的価値をどう高め、部下との信頼関係を築くべきかを考察します。",
    "source_topics": [
      "若手社員のAI活用と上司への信頼度調査",
      "課長のAI活用実態と部下育成への懸念"
    ],
    "connected_resource": "1on1総研 調査レポート（各種）",
    "why_now": "AIの進化が加速し、職場での活用が広がる中で、マネジャーの役割と求められるスキルが大きく変化しているためです。"
  },
  {
    "type": "branding",
    "title": "プロティアン・キャリア支援の最前線：AI時代にマネジャーが部下のキャリア自律をどう促すか",
    "target_reader": "マネジャー・管理職、人事担当者",
    "angle": "AIを活用したキャリア支援の潮流や、企業の社内公募制度導入事例を参考に、マネジャーが部下のキャリア自律をどのようにサポートし、その本質的な役割を果たすべきかを深掘りします。",
    "source_topics": [
      "AIを活用したキャリア支援の動向",
      "イケア・ジャパンの社内公募制度導入事例"
    ],
    "connected_resource": "メンバーのための1on1完全ガイド",
    "why_now": "キャリアの不確実性が高まる現代において、従業員のキャリア自律支援は企業にとって不可欠なテーマだからです。"
  },
  {
    "type": "branding",
    "title": "「罰ゲーム化する管理職」を乗り越えろ！強いミドルマネジメントを復活させる組織戦略",
    "target_reader": "経営層、人事担当者、マネジャー・管理職",
    "angle": "管理職の負担増大とモチベーション低下が指摘される中、管理職が本来のリーダーシップを発揮し、組織の中核として機能するための組織的・個人的なアプローチを提唱します。",
    "source_topics": [
      "管理職の負担増と「罰ゲーム化」の指摘"
    ],
    "connected_resource": "マネジャーのための1on1完全ガイド",
    "why_now": "ミドルマネジメント層の疲弊は組織全体の生産性やエンゲージメントに直結するため、早急な対策が求められています。"
  },
  {
    "type": "branding",
    "title": "心的資本経営とは？従業員の「ハピネス」が組織を強くするトリドールHDの挑戦",
    "target_reader": "経営層、人事担当者、マネジャー・管理職",
    "angle": "トリドールホールディングスの「心的資本経営（ハピカン経営）」を事例に、従業員の幸福感（ハピネス）を経営戦略の中心に据える考え方と、それが組織の生産性や顧客体験にもたらす効果を解説します。",
    "source_topics": [
      "トリドールHDの心的資本経営への取り組み"
    ],
    "connected_resource": "1on1総研 調査レポート（各種）",
    "why_now": "人的資本経営の重要性が高まる中、従業員のエンゲージメントや幸福感を高める経営手法が注目されているためです。"
  },
  {
    "type": "branding",
    "title": "ダイバーシティ＆インクルージョン時代のリーダーシップ：多様性を活かす「関係性」のマネジメント術",
    "target_reader": "経営層、人事担当者、マネジャー・管理職",
    "angle": "ジェンダー平等や多様性の推進が求められる中で、リーダーがどのように多様な人材を活かし、組織のパフォーマンスを高めるか。「関係のダイバーシティ」という新たな視点からリーダーシップを考察します。",
    "source_topics": [
      "多様性を活かすリーダー行動のアップデート",
      "ダイバーシティ推進における「手応えの無さ」"
    ],
    "connected_resource": "上司・部下の信頼関係16段階シート",
    "why_now": "多様な人材が活躍できる組織づくりは、企業の持続的成長に不可欠な経営課題だからです。"
  },
  {
    "type": "branding",
    "title": "「年収500万円ください」自己申告型報酬制度の衝撃：納得感とエンゲージメントを高める賃金制度の未来",
    "target_reader": "経営層、人事担当者",
    "angle": "自己申告型報酬制度の導入事例から、従業員のモチベーションやエンゲージメントを高める新たな報酬制度の設計と、それに伴うマネジメントの役割、そして成果を可視化する重要性を探ります。",
    "source_topics": [
      "自己申告型報酬制度の導入事例"
    ],
    "connected_resource": "KAKEAIサービス資料",
    "why_now": "人材不足と物価上昇が続く中、従業員が納得感を持って働ける評価・給与制度の構築が喫緊の課題となっているためです。"
  },
  {
    "type": "lead",
    "title": "「成長実感がない」が退職理由の本音？1on1でキャリア自律を促すマネジャーの対話術",
    "target_reader": "マネジャー・管理職、人事担当者",
    "angle": "「成長の実感がない」という退職理由が上位である現状に対し、マネジャーが1on1でどのように部下の成長を支援し、キャリア自律を促すか、具体的な質問例や対話のフレームワークを紹介します。",
    "source_topics": [
      "退職理由の本音と建前に関する調査",
      "キャリア面談の効果を高める方法"
    ],
    "connected_resource": "マネジャー向け1on1質問集",
    "why_now": "従業員の成長意欲とキャリア自律への関心が高まる中、1on1を通じた効果的な支援が離職防止に繋がるためです。"
  },
  {
    "type": "lead",
    "title": "新人・若手のスピード退職を防ぐ！早期定着を促す1on1の進め方と効果的なアプローチ",
    "target_reader": "マネジャー・管理職、人事担当者",
    "angle": "入社3ヶ月以内の早期退職が多い現状を受け、新入社員や若手の不安を解消し、早期定着を促すための1on1の進め方と、具体的なオンボーディング支援や信頼関係構築のアプローチを解説します。",
    "source_topics": [
      "新人・若手の早期離職に関する調査",
      "20代若手社員のスピード退職動向"
    ],
    "connected_resource": "メンバーのための1on1完全ガイド",
    "why_now": "新入社員の早期離職は組織にとって大きな損失であり、定着率向上は重要な経営課題だからです。"
  },
  {
    "type": "lead",
    "title": "「職場の孤独」を生まないマネジメント：1on1で部下との心理的距離を縮める対話術",
    "target_reader": "マネジャー・管理職、人事担当者",
    "angle": "職場の孤独が生産性低下や離職につながる深刻な課題に対し、マネジャーが1on1を通じて部下との信頼関係を築き、孤立を防ぐための具体的な対話のコツと、安心できる環境づくりのポイントを紹介します。",
    "source_topics": [
      "職場の孤独が組織に与える影響に関する指摘"
    ],
    "connected_resource": "上司・部下の信頼関係16段階シート",
    "why_now": "従業員のメンタルヘルスやエンゲージメントの重要性が高まる中で、職場の孤独対策は組織の健全性維持に不可欠です。"
  },
  {
    "type": "lead",
    "title": "パワハラと紙一重？「マイクロアグレッション」をなくすマネジャーの言動チェックリスト",
    "target_reader": "マネジャー・管理職、人事担当者",
    "angle": "ハラスメントとまでは言えないが、部下を傷つけ信頼関係を損ねる「マイクロアグレッション」について解説し、マネジャーがそれを避けるための具体的な言動チェックリストと、対話における注意点を提供します。",
    "source_topics": [
      "ハラスメントとまでは呼べない言動に関する指摘"
    ],
    "connected_resource": "マネジャーのための1on1完全ガイド",
    "why_now": "ハラスメント防止法が施行され、職場での不適切な言動への意識が高まる中、より繊細な配慮が求められているためです。"
  },
  {
    "type": "lead",
    "title": "「健全な対立」が組織を強くする！風通しの良い職場を作る1on1対話のコツ",
    "target_reader": "マネジャー・管理職、人事担当者",
    "angle": "意見の衝突を恐れず、建設的な議論ができる「風通しの良い組織」を作るために、マネジャーが1on1で健全な対立をどのように促し、チームの創造性や問題解決能力を高めるか、具体的な対話のコツを伝授します。",
    "source_topics": [
      "風通しの良い組織を作る4つのポイント"
    ],
    "connected_resource": "マネジャー向け1on1質問集",
    "why_now": "変化の激しい時代において、組織の適応力やイノベーション創出のためには、活発な意見交換と健全な対立が不可欠だからです。"
  },
  {
    "type": "lead",
    "title": "AIに「相談相手」を奪われるな！若手から真に信頼されるマネジャーになるための1on1術",
    "target_reader": "マネジャー・管理職",
    "angle": "若手社員が上司よりも生成AIに相談することを信頼する傾向がある中で、マネジャーが部下から真に信頼される対話相手となるための1on1の心構えと実践法を紹介します。AIにはできない「人間らしい対話」の価値を再定義します。",
    "source_topics": [
      "若手社員のAI活用と上司への信頼度調査"
    ],
    "connected_resource": "マネジャーのための1on1完全ガイド",
    "why_now": "AIが普及し、情報収集や自己解決の手段が増える中で、マネジャーが部下にとって価値ある存在であり続けるための対話力が重要視されているためです。"
  },
  {
    "type": "lead",
    "title": "転勤拒否の時代にどう向き合う？納得感を高める1on1でのキャリア対話術",
    "target_reader": "マネジャー・管理職、人事担当者",
    "angle": "転職希望者の約7割が転勤を嫌がるとの調査結果を受け、企業が転勤制度を維持しつつ、従業員の納得感を高めるための1on1でのキャリア対話の重要性を解説します。個人のキャリア志向と組織のニーズをどうすり合わせるか。",
    "source_topics": [
      "転勤と転職に関する調査レポート"
    ],
    "connected_resource": "メンバーのための1on1完全ガイド",
    "why_now": "働き方の多様化やライフワークバランス重視の傾向が強まる中で、転勤制度は人材確保・定着における重要な論点となっているためです。"
  }
]